MANIFEST.in
README.rst
setup.py
collective/.DS_Store
collective/__init__.py
collective/__init__.pyc
collective.ptg.supersized.egg-info/PKG-INFO
collective.ptg.supersized.egg-info/SOURCES.txt
collective.ptg.supersized.egg-info/dependency_links.txt
collective.ptg.supersized.egg-info/entry_points.txt
collective.ptg.supersized.egg-info/namespace_packages.txt
collective.ptg.supersized.egg-info/not-zip-safe
collective.ptg.supersized.egg-info/requires.txt
collective.ptg.supersized.egg-info/top_level.txt
collective/ptg/.DS_Store
collective/ptg/__init__.py
collective/ptg/__init__.pyc
collective/ptg/supersized/.DS_Store
collective/ptg/supersized/__init__.py
collective/ptg/supersized/__init__.pyc
collective/ptg/supersized/configure.zcml
collective/ptg/supersized/i18n.sh
collective/ptg/supersized/supersized.pt
collective/ptg/supersized/locales/collective.ptg.supersized.pot
collective/ptg/supersized/locales/manual.pot
collective/ptg/supersized/locales/de/LC_MESSAGES/collective.ptg.supersized.po
collective/ptg/supersized/locales/es/LC_MESSAGES/collective.ptg.supersized.po
collective/ptg/supersized/locales/eu/LC_MESSAGES/collective.ptg.supersized.po
collective/ptg/supersized/locales/fi/LC_MESSAGES/collective.ptg.supersized.po
collective/ptg/supersized/locales/fr/LC_MESSAGES/collective.ptg.supersized.po
collective/ptg/supersized/locales/it/LC_MESSAGES/collective.ptg.supersized.po
collective/ptg/supersized/locales/nl/LC_MESSAGES/collective.ptg.supersized.po
collective/ptg/supersized/locales/no/LC_MESSAGES/collective.ptg.supersized.po
collective/ptg/supersized/locales/pt_BR/LC_MESSAGES/collective.ptg.supersized.po
collective/ptg/supersized/resources/.DS_Store
collective/ptg/supersized/resources/GPL-LICENSE.txt
collective/ptg/supersized/resources/MIT-LICENSE.txt
collective/ptg/supersized/resources/just_a_test.pt
collective/ptg/supersized/resources/css/supersized.css
collective/ptg/supersized/resources/js/supersized.js
collective/ptg/supersized/resources/js/supersized.min.js
collective/ptg/supersized/resources/plone/back.png
collective/ptg/supersized/resources/plone/bg-black.png
collective/ptg/supersized/resources/plone/bg-hover.png
collective/ptg/supersized/resources/plone/button-tray-down.png
collective/ptg/supersized/resources/plone/button-tray-up.png
collective/ptg/supersized/resources/plone/forward.png
collective/ptg/supersized/resources/plone/nav-bg.png
