Metadata-Version: 1.1
Name: collective.ptg.supersized
Version: 1.2
Summary: UNKNOWN
Home-page: https://github.com/collective/collective.ptg.supersized
Author: Nathan Van Gheem
Author-email: vangheem@gmail.com
License: GPL
Keywords: plone plonetruegallery supersized
Platform: UNKNOWN
Classifier: Framework :: Plone
Classifier: Programming Language :: Python
